quartofetch/__init__.py
quartofetch/cli.py
quartofetch/exceptions.py
quartofetch/logging_config.py
quartofetch/paper_manager.py
quartofetch/quarto_project.py
quartofetch-0.1.4.dist-info/METADATA
quartofetch-0.1.4.dist-info/WHEEL
quartofetch-0.1.4.dist-info/entry_points.txt
quartofetch-0.1.4.dist-info/licenses/LICENSE
quartofetch-0.1.4.dist-info/RECORD
