Metadata-Version: 2.3
Name: quartofetch
Version: 0.1.4
Summary: Fetch and manage Quarto paper repositories
Author-email: Andrew Mitchell <a.j.mitchell@ucl.ac.uk>
License-Expression: MIT
License-File: LICENSE
Classifier: Development Status :: 4 - Beta
Classifier: Intended Audience :: Developers
Classifier: License :: OSI Approved :: MIT License
Classifier: Programming Language :: Python :: 3.12
Classifier: Topic :: Software Development :: Libraries :: Python Modules
Requires-Python: >=3.10
Requires-Dist: loguru>=0.7.2
Requires-Dist: pyyaml>=6.0.2
